cmake2chat.py
cmake2chat-0.1.0a0.dist-info/licenses/LICENSE
cmake2chat-0.1.0a0.dist-info/METADATA
cmake2chat-0.1.0a0.dist-info/WHEEL
cmake2chat-0.1.0a0.dist-info/top_level.txt
cmake2chat-0.1.0a0.dist-info/RECORD
