Metadata-Version: 2.4
Name: cmake2chat
Version: 0.1.0a0
Summary: Scans your CMake project directory, builds a tree view of the codebase, and exports the tree view, the paths of all `CMakeLists.txt` files along with their contents to an OpenAI Chat Completions-compatible JSON.
Author-email: Jifeng Wu <jifengwu2k@gmail.com>
License-Expression: MIT
Project-URL: Homepage, https://github.com/jifengwu2k/cmake2chat
Project-URL: Bug Tracker, https://github.com/jifengwu2k/cmake2chat/issues
Classifier: Programming Language :: Python :: 2
Classifier: Programming Language :: Python :: 3
Classifier: Operating System :: OS Independent
Requires-Python: >=2
License-File: LICENSE
Requires-Dist: build-filesystem-trie
Requires-Dist: cowlist
Dynamic: license-file
